yamllinttojunitxml/__init__.py
yamllinttojunitxml/yamllinttojunitxml.py
yaml_lint_to_junit_xml-0.1.1.dist-info/LICENSE
yaml_lint_to_junit_xml-0.1.1.dist-info/METADATA
yaml_lint_to_junit_xml-0.1.1.dist-info/WHEEL
yaml_lint_to_junit_xml-0.1.1.dist-info/entry_points.txt
yaml_lint_to_junit_xml-0.1.1.dist-info/top_level.txt
yaml_lint_to_junit_xml-0.1.1.dist-info/RECORD
