Metadata-Version: 2.1
Name: yaml-lint-to-junit-xml
Version: 0.1.1
Summary: Convert yaml-lint outputs to a jUnit valid xml tests result file
Home-page: https://github.com/shipilovds/yaml-lint-to-junit-xml
Author: Denis Shipilov
Author-email: shipilovds@gmail.com
License: MIT
Keywords: yaml,lint,junit,report
Platform: UNKNOWN
Classifier: Development Status :: 2 - Pre-Alpha
Classifier: Intended Audience :: Developers
Classifier: License :: OSI Approved :: MIT License
Classifier: Natural Language :: English
Classifier: Programming Language :: Python :: 2
Classifier: Programming Language :: Python :: 2.6
Classifier: Programming Language :: Python :: 2.7
Classifier: Programming Language :: Python :: 3
Classifier: Programming Language :: Python :: 3.3
Classifier: Programming Language :: Python :: Implementation :: PyPy
